beaker_pysb/__about__.py
beaker_pysb/__init__.py
beaker_pysb/agent.py
beaker_pysb/context.py
beaker_pysb-0.0.1.data/data/share/beaker/bunsen/beaker_pysb.json
beaker_pysb-0.0.1.data/data/share/beaker/contexts/beaker_pysb.json
beaker_pysb-0.0.1.data/data/share/beaker/corpuses/beaker_pysb/config.yaml
beaker_pysb-0.0.1.data/data/share/beaker/corpuses/beaker_pysb/store.zip
beaker_pysb-0.0.1.data/data/share/beaker/corpuses/beaker_pysb/resources/code/pysb
beaker_pysb-0.0.1.data/data/share/beaker/corpuses/beaker_pysb/resources/code/pysb._version
beaker_pysb-0.0.1.data/data/share/beaker/corpuses/beaker_pysb/resources/code/pysb.anneal_mod
beaker_pysb-0.0.1.data/data/share/beaker/corpuses/beaker_pysb/resources/code/pysb.annotation
beaker_pysb-0.0.1.data/data/share/beaker/corpuses/beaker_pysb/resources/code/pysb.bng
beaker_pysb-0.0.1.data/data/share/beaker/corpuses/beaker_pysb/resources/code/pysb.builder
beaker_pysb-0.0.1.data/data/share/beaker/corpuses/beaker_pysb/resources/code/pysb.core
beaker_pysb-0.0.1.data/data/share/beaker/corpuses/beaker_pysb/resources/code/pysb.examples.bax_pore
beaker_pysb-0.0.1.data/data/share/beaker/corpuses/beaker_pysb/resources/code/pysb.examples.bax_pore_sequential
beaker_pysb-0.0.1.data/data/share/beaker/corpuses/beaker_pysb/resources/code/pysb.examples.bngwiki_egfr_simple
beaker_pysb-0.0.1.data/data/share/beaker/corpuses/beaker_pysb/resources/code/pysb.examples.bngwiki_enzymatic_cycle_mm
beaker_pysb-0.0.1.data/data/share/beaker/corpuses/beaker_pysb/resources/code/pysb.examples.bngwiki_simple
beaker_pysb-0.0.1.data/data/share/beaker/corpuses/beaker_pysb/resources/code/pysb.examples.earm_1_0
beaker_pysb-0.0.1.data/data/share/beaker/corpuses/beaker_pysb/resources/code/pysb.examples.earm_1_3
beaker_pysb-0.0.1.data/data/share/beaker/corpuses/beaker_pysb/resources/code/pysb.examples.explicit
beaker_pysb-0.0.1.data/data/share/beaker/corpuses/beaker_pysb/resources/code/pysb.examples.expression_observables
beaker_pysb-0.0.1.dist-info/METADATA
beaker_pysb-0.0.1.dist-info/WHEEL
beaker_pysb-0.0.1.dist-info/licenses/LICENSE.txt
beaker_pysb-0.0.1.dist-info/RECORD
