Metadata-Version: 2.3
Name: beaker-pysb
Version: 0.0.1
Project-URL: Documentation, https://github.com/unknown/beaker-pysb#readme
Project-URL: Issues, https://github.com/unknown/beaker-pysb/issues
Project-URL: Source, https://github.com/unknown/beaker-pysb
Author-email: Matthew Printz <matt@jataware.com>
License-Expression: MIT
License-File: LICENSE.txt
Classifier: Development Status :: 4 - Beta
Classifier: Programming Language :: Python
Classifier: Programming Language :: Python :: 3.10
Classifier: Programming Language :: Python :: 3.11
Classifier: Programming Language :: Python :: 3.12
Classifier: Programming Language :: Python :: Implementation :: CPython
Classifier: Programming Language :: Python :: Implementation :: PyPy
Requires-Python: >=3.10
Requires-Dist: beaker-bunsen>=0.0.6
Requires-Dist: pysb
